lib/__init__.py
lib/egypt_codes.py
lib/national_id.py
national_id-1.0.2.dist-info/LICENSE
national_id-1.0.2.dist-info/WHEEL
national_id-1.0.2.dist-info/METADATA
national_id-1.0.2.dist-info/RECORD
