Metadata-Version: 2.1
Name: national-id
Version: 1.0.2
Summary: Egyptian national ID validator and data-extractor AP
Home-page: https://github.com/waleedhammam/national_id
License: Apache-2.0
Keywords: python,bottle,nationalid
Author: waleedhammam
Author-email: waleed.hammam@gmail.com
Requires-Python: >=3.8,<4.0
Classifier: License :: OSI Approved :: Apache Software License
Classifier: Programming Language :: Python :: 3
Classifier: Programming Language :: Python :: 3.8
Requires-Dist: WebTest (==2.0.35)
Requires-Dist: bottle (==0.12.17)
Requires-Dist: loguru (==0.5.3)
Requires-Dist: pytest (==5.4.3)
Requires-Dist: pytest-cov (==2.10.1)
Requires-Dist: requests (==2.23.0)
Project-URL: Repository, https://github.com/waleedhammam/national_id
